archinstall/__init__.py
archinstall/__main__.py
archinstall/applications/audio.py
archinstall/applications/bluetooth.py
archinstall/applications/power_management.py
archinstall/applications/print_service.py
archinstall/default_profiles/__init__.py
archinstall/default_profiles/custom.py
archinstall/default_profiles/desktop.py
archinstall/default_profiles/minimal.py
archinstall/default_profiles/profile.py
archinstall/default_profiles/server.py
archinstall/default_profiles/tailored.py
archinstall/default_profiles/xorg.py
archinstall/default_profiles/desktops/__init__.py
archinstall/default_profiles/desktops/awesome.py
archinstall/default_profiles/desktops/bspwm.py
archinstall/default_profiles/desktops/budgie.py
archinstall/default_profiles/desktops/cinnamon.py
archinstall/default_profiles/desktops/cosmic.py
archinstall/default_profiles/desktops/cutefish.py
archinstall/default_profiles/desktops/deepin.py
archinstall/default_profiles/desktops/enlightenment.py
archinstall/default_profiles/desktops/gnome.py
archinstall/default_profiles/desktops/hyprland.py
archinstall/default_profiles/desktops/i3.py
archinstall/default_profiles/desktops/labwc.py
archinstall/default_profiles/desktops/lxqt.py
archinstall/default_profiles/desktops/mate.py
archinstall/default_profiles/desktops/niri.py
archinstall/default_profiles/desktops/plasma.py
archinstall/default_profiles/desktops/qtile.py
archinstall/default_profiles/desktops/river.py
archinstall/default_profiles/desktops/sway.py
archinstall/default_profiles/desktops/xfce4.py
archinstall/default_profiles/desktops/xmonad.py
archinstall/default_profiles/servers/__init__.py
archinstall/default_profiles/servers/cockpit.py
archinstall/default_profiles/servers/docker.py
archinstall/default_profiles/servers/httpd.py
archinstall/default_profiles/servers/lighttpd.py
archinstall/default_profiles/servers/mariadb.py
archinstall/default_profiles/servers/nginx.py
archinstall/default_profiles/servers/postgresql.py
archinstall-3.0.15.dist-info/licenses/LICENSE
archinstall-3.0.15.dist-info/METADATA
archinstall-3.0.15.dist-info/WHEEL
archinstall-3.0.15.dist-info/entry_points.txt
archinstall-3.0.15.dist-info/top_level.txt
archinstall-3.0.15.dist-info/RECORD
