Metadata-Version: 2.4
Name: archinstall
Version: 3.0.15
Summary: Arch Linux installer - guided, templates etc.
Author-email: Anton Hvornum <anton@hvornum.se>
License-Expression: GPL-3.0-only
Project-URL: Home, https://archlinux.org
Project-URL: Documentation, https://archinstall.readthedocs.io/
Project-URL: Source, https://github.com/archlinux/archinstall
Keywords: linux,arch,archinstall,installer
Classifier: Programming Language :: Python :: 3.12
Classifier: Operating System :: POSIX :: Linux
Requires-Python: >=3.12
License-File: LICENSE
Requires-Dist: pyparted>=3.13.0
Requires-Dist: pydantic==2.12.5
Requires-Dist: cryptography>=45.0.7
Requires-Dist: textual>=5.3.0
Requires-Dist: pytest-mock>=3.15.1
Provides-Extra: log
Requires-Dist: systemd_python==235; extra == "log"
Provides-Extra: dev
Requires-Dist: mypy==1.19.1; extra == "dev"
Requires-Dist: flake8==7.3.0; extra == "dev"
Requires-Dist: pre-commit==4.5.1; extra == "dev"
Requires-Dist: ruff==0.14.10; extra == "dev"
Requires-Dist: pylint==4.0.4; extra == "dev"
Requires-Dist: pytest==9.0.2; extra == "dev"
Provides-Extra: doc
Requires-Dist: sphinx; extra == "doc"
Dynamic: license-file
